{
  "away_lineup_completeness": 0.020223,
  "home_lineup_completeness": 0.016536,
  "diff_sp_sc_xwoba": 0.011425,
  "combined_sp_sc_xwoba": 0.010037,
  "away_win_pct_last_5": 0.008569,
  "away_sp_venue_starts": 0.007248,
  "home_sp_era_20": 0.007189,
  "diff_lineup_xwoba": 0.006918,
  "home_elo_x_sp_quality": 0.005848,
  "home_h2h_ba": 0.005742,
  "run_line_move_direction": 0.005654,
  "away_bullpen_exposure": 0.005258,
  "abs_run_line_move": 0.005129,
  "away_top4_x_opp_bp": 0.005124,
  "home_h2h_slg": 0.005075,
  "away_elo_x_sp_quality": 0.004912,
  "home_team_hr_x_park": 0.004737,
  "home_sp_fip_10": 0.004552,
  "away_sp_sc_xwoba": 0.004476,
  "series_game_number": 0.004424,
  "home_sp_last_k": 0.004401,
  "sp_fip_edge_5": 0.004222,
  "home_rest_days": 0.004164,
  "obp_edge_10": 0.00408,
  "home_sp_days_rest": 0.003968,
  "combined_slg_avg_10": 0.003961,
  "home_sp_fip_20": 0.003948,
  "fb_velo_trend_diff": 0.003943,
  "away_run_diff": 0.003888,
  "away_bp_relievers_last_1d": 0.003836,
  "team_k_bb_ratio_diff": 0.003824,
  "diff_sp_sc_k_pct": 0.003807,
  "away_h2h_slg_wtd": 0.003787,
  "home_lineup_xwoba_avg": 0.003779,
  "combined_sp_sc_whiff_pct": 0.00365,
  "home_bp_avg_era_last_3d": 0.003608,
  "away_sp_era_opp_adj_5": 0.003596,
  "away_sp_venue_k9": 0.003529,
  "home_top4_slg_avg_10": 0.003513,
  "away_wins": 0.00347,
  "away_lineup_xwoba_avg": 0.00347,
  "home_bullpen_exposure": 0.003464,
  "bp_relievers_edge_3d": 0.003444,
  "away_wins_last_10": 0.003423,
  "home_implied_runs": 0.003421,
  "ump_rpg_10": 0.003408,
  "home_sp_fip_5": 0.003331,
  "home_pen_depletion": 0.003326,
  "away_elo": 0.003311,
  "combined_runs_avg_5": 0.003262,
  "abs_total_line_move": 0.003258,
  "win_pct_last_5_diff": 0.003257,
  "bp_relievers_edge_2d": 0.003256,
  "home_sp_fb_put_away": 0.003248,
  "home_bp_relievers_last_2d": 0.003245,
  "home_sp_era_opp_adj_5": 0.003242,
  "away_sp_venue_advantage": 0.003231,
  "sp_era_trend_diff": 0.003197,
  "pen_depletion_edge": 0.00318,
  "batting_runs_avg_5_diff": 0.003163,
  "home_sp_sc_xwoba": 0.003158,
  "diff_sp_sc_exit_velo": 0.003134,
  "combined_sp_sc_oz_swing_pct": 0.003134,
  "elo_diff": 0.00309,
  "team_whip_5_diff": 0.003082,
  "home_wins": 0.00308,
  "home_sp_fip_away_10": 0.003078,
  "run_diff_per_game_edge": 0.003069,
  "home_bp_hot_1d": 0.00306,
  "home_win_pct_last_10": 0.003054,
  "home_run_diff": 0.003038,
  "b2b_asymmetry": 0.003003,
  "away_sp_fip_trend_5v10": 0.003,
  "away_sp_venue_fip": 0.002994,
  "away_sp_pitches_est": 0.002952,
  "home_k9_10": 0.002922,
  "away_sb_trend": 0.002914,
  "away_fb_velo_avg_5": 0.002891,
  "away_catcher_framing_rv": 0.002876,
  "home_sp_sc_k_bb_ratio": 0.00286,
  "pythag_sp_quality_diff": 0.002845,
  "ops_diff_5": 0.002822,
  "away_lineup_xslg_avg": 0.00282,
  "home_sp_era_5v20": 0.002819,
  "home_catcher_framing_rv": 0.002819,
  "diff_sp_sc_k_bb_ratio": 0.002804,
  "away_sp_career_whip_5": 0.0028,
  "away_sp_last_ip": 0.002768,
  "away_sp_sc_barrel_rate": 0.002765,
  "away_sp_era_park_adj_5": 0.002764,
  "home_bp_era7_x_ip7": 0.002762,
  "home_sp_home_away_era_split": 0.002754,
  "away_sp_bb9_5": 0.002739,
  "sp_era_opp_adj_diff": 0.002725,
  "home_runs_trend_5v20": 0.002717,
  "home_bp_usage_per_rest": 0.002707,
  "away_top4_slg_avg_10": 0.002701,
  "home_ops_10": 0.002697,
  "home_win_pct": 0.002694,
  "away_bp_whip_10": 0.002692,
  "away_sp_k_pct_10": 0.002691,
  "away_h2h_n": 0.002689,
  "away_bp_hot_1d": 0.002685,
  "away_bb9_10": 0.002678,
  "away_win_pct": 0.002657,
  "ump_sp_k_environment": 0.002649,
  "away_sp_sc_exit_velo": 0.002648,
  "total_k_suppression": 0.002643,
  "home_sp_k9_5": 0.002642,
  "ump_k9_x_home_sp_k": 0.00264,
  "era_edge_10": 0.002633,
  "away_pen_qual_depletion": 0.002611,
  "home_sp_k_pct_trend": 0.002607,
  "away_run_diff_avg_last_5": 0.002603,
  "away_slg_avg_10": 0.002593,
  "pythag_record_edge": 0.002576,
  "away_sp_home_away_era_split": 0.002576,
  "home_lineup_avg_avg_10": 0.002573,
  "home_sp_ch_whiff_pct": 0.002556,
  "home_fb_velo_trend_5": 0.002546,
  "away_bp_ip_last_1d": 0.002546,
  "bp_avg_era_last_3d_diff": 0.002533,
  "away_sp_hr9_5": 0.002526,
  "combined_sp_sc_exit_velo": 0.002521,
  "away_hr9_10": 0.002506,
  "lineup_slg_edge": 0.002459,
  "combined_sp_era_10": 0.002454,
  "combined_sp_sc_barrel_rate": 0.00245,
  "pen_qual_depletion_edge": 0.002443,
  "home_runs_avg_20": 0.002432,
  "home_catcher_framing_rate": 0.002427,
  "away_fb_velo_trend_5": 0.002427,
  "away_era_trend_5v10": 0.002422,
  "home_bp_era_7d": 0.002421,
  "home_pythag_vs_record": 0.002418,
  "win_pct_last_10_diff": 0.002412,
  "away_sp_whip_5": 0.002411,
  "sp_form_edge": 0.00241,
  "home_lineup_barrel_avg": 0.00241,
  "temperature_f": 0.002399,
  "away_win_pct_last_10": 0.002392,
  "away_sp_fip_20": 0.002383,
  "home_team_k_bb_ratio_5": 0.002369,
  "total_k_env_park_adj": 0.002358,
  "sp_composite_edge": 0.002358,
  "home_sp_hr9_5": 0.002353,
  "away_sp_sc_k_bb_ratio": 0.002351,
  "home_sb_pct_10": 0.002348,
  "away_iso_avg_10": 0.002339,
  "home_fb_velo_avg_5": 0.002329,
  "runs_scored_edge_10": 0.002328,
  "home_sp_ip_per_rest": 0.00232,
  "away_sp_era_20": 0.002319,
  "home_sp_whip_5": 0.002309,
  "total_k_env": 0.002305,
  "home_sp_k_bb_ratio_5": 0.002305,
  "ump_k9_x_away_sp_k": 0.002299,
  "away_sp_era_5v20": 0.002286,
  "home_iso_avg_10": 0.002284,
  "combined_ops_10": 0.002277,
  "whip_edge_10": 0.002274,
  "away_sp_era_x_opp_avg": 0.002269,
  "combined_sp_sc_bb_pct": 0.002268,
  "home_sp_sc_hard_hit_pct": 0.002263,
  "away_catcher_framing_rate": 0.002256,
  "home_games_played": 0.002247,
  "runs_trend_diff": 0.002239,
  "home_sp_sl_whiff_pct": 0.002239,
  "home_sp_era_10": 0.002237,
  "away_sp_fb_put_away": 0.002222,
  "home_form_vs_season": 0.00222,
  "away_sp_era_away_10": 0.002219,
  "home_sp_k_pct_5": 0.002218,
  "combined_sp_sc_k_pct": 0.002199,
  "away_avg_avg_5": 0.002193,
  "away_sb_avg_5": 0.002191,
  "wind_sin": 0.002182,
  "ump_rpg_x_park": 0.002181,
  "park_adj_implied_total": 0.002177,
  "home_hr9_5": 0.002171,
  "home_top4_x_opp_bp": 0.002164,
  "away_hr9_5": 0.002162,
  "home_sp_k_pct_10": 0.002158,
  "away_sp_k9_home_10": 0.002136,
  "sp_era_edge_5": 0.002134,
  "away_sp_k_pct_trend": 0.002133,
  "abs_fb_velo_trend_home": 0.002128,
  "home_sp_era_home_10": 0.002125,
  "away_h2h_obp": 0.002122,
  "home_sp_k9_away_10": 0.002122,
  "home_sp_career_era_5": 0.002121,
  "home_sp_sc_barrel_rate": 0.002115,
  "away_bb9_5": 0.002104,
  "diff_lineup_hard_hit": 0.002103,
  "sp_pitches_est_diff": 0.002099,
  "home_pythag_x_opp_sp_fip": 0.002095,
  "home_sp_pitches_est": 0.002081,
  "form_momentum_diff": 0.002067,
  "away_sp_fip_away_10": 0.002063,
  "diff_sp_sc_hard_hit_pct": 0.002044,
  "home_bullpen_ip_last_7": 0.002043,
  "diff_lineup_barrel": 0.002038,
  "home_team_sp_k9_10": 0.002018,
  "combined_bp_k9": 0.002016,
  "season_2026-regular": 0.002012,
  "home_park_adj_runs_10": 0.002009,
  "away_run_diff_per_game": 0.001992,
  "ump_rpg_5": 0.001989,
  "away_obp_avg_5": 0.001989,
  "home_bp_era_5": 0.001988,
  "home_bp_k9_10": 0.001983,
  "wind_cos": 0.00198,
  "home_sp_last_k_rate": 0.001965,
  "home_sp_k9_home_10": 0.001944,
  "away_bp_relievers_last_2d": 0.001931,
  "catcher_framing_rv_diff": 0.00193,
  "home_era_trend_5v10": 0.001912,
  "away_bp_whip_5": 0.001905,
  "batting_hr_avg_5_diff": 0.001901,
  "home_bb9_10": 0.001898,
  "start_hour_utc": 0.001896,
  "away_sp_sc_k_pct": 0.001883,
  "home_team_sp_k9_5": 0.001879,
  "sb_rate_diff": 0.001874,
  "away_runs_sd_10": 0.00187,
  "away_bp_k9_10": 0.001866,
  "precip_prob_pct": 0.001864,
  "away_lineup_slg_avg_10": 0.00186,
  "home_sp_sc_oz_swing_pct": 0.00186,
  "bp_era_diff_10": 0.001858,
  "away_sp_k_bb_ratio_5": 0.00185,
  "bp_relievers_edge_1d": 0.001847,
  "ump_bb9_x_home_team_bb": 0.001841,
  "home_era_5": 0.00184,
  "home_obp_avg_10": 0.001832,
  "away_iso_avg_5": 0.001828,
  "away_bullpen_ip_last_3": 0.001825,
  "home_bp_whip_10": 0.001823,
  "diff_sp_sc_oz_swing_pct": 0.00181,
  "away_sp_venue_era": 0.001807,
  "away_lineup_iso_avg_10": 0.001802,
  "away_bp_era_10": 0.001793,
  "era_trend_diff": 0.001784,
  "wind_scoring_boost": 0.001784,
  "combined_ch_whiff_pct": 0.001784,
  "sp_k_bb_ratio_diff": 0.001781,
  "home_whip_10": 0.001778,
  "away_sp_career_era_10": 0.001777,
  "away_pen_exposure_x_era": 0.001775,
  "away_bp_avg_era_last_3d": 0.001773,
  "home_lineup_xslg_avg": 0.001759,
  "home_lineup_hard_hit_avg": 0.001748,
  "home_sp_fip_trend_5v10": 0.001738,
  "bullpen_fatigue_edge": 0.001736,
  "sp_era_park_adj_diff": 0.001732,
  "home_hr9_10": 0.00173,
  "wind_speed_mph": 0.001721,
  "away_team_hr_x_park": 0.001719,
  "home_pen_qual_depletion": 0.001713,
  "combined_sp_era_5": 0.001713,
  "away_sp_sc_hard_hit_pct": 0.001698,
  "home_bp_ip_last_1d": 0.001695,
  "away_sp_era_trend_5v10": 0.001691,
  "combined_sp_sc_hard_hit_pct": 0.001677,
  "home_sp_venue_advantage": 0.001663,
  "home_sp_venue_k9": 0.00166,
  "ump_k9_10": 0.001656,
  "home_run_diff_per_game": 0.001654,
  "home_bp_relievers_last_3d": 0.001647,
  "home_sp_ip_avg_5": 0.001644,
  "ump_bb9_10": 0.001641,
  "away_lineup_barrel_avg": 0.001636,
  "away_sp_last_fip": 0.001635,
  "home_sp_bb_pct_5": 0.001627,
  "sp_k_pct_trend_diff": 0.001611,
  "h2h_slg_edge_wtd": 0.001601,
  "away_sp_era_10": 0.001597,
  "home_pen_exposure_x_era": 0.001594,
  "away_pythag_x_opp_sp_fip": 0.001594,
  "combined_catcher_framing_rv": 0.001586,
  "sp_workload_edge": 0.001584,
  "home_h2h_obp": 0.001582,
  "away_era_10": 0.001578,
  "diff_sp_sc_whiff_pct": 0.001565,
  "away_sp_era_5": 0.001562,
  "home_h2h_slg_wtd": 0.001562,
  "home_sp_era_x_opp_avg": 0.00156,
  "away_sp_whip_10": 0.001559,
  "away_sp_career_era_5": 0.001558,
  "home_sp_sc_k_pct": 0.001555,
  "away_h2h_ba": 0.001554,
  "start_dow_utc": 0.001544,
  "away_pen_depletion": 0.001543,
  "ump_bb9_5": 0.001541,
  "home_sp_last_fip": 0.00154,
  "home_win_pct_last_5": 0.001538,
  "park_adj_total_env": 0.001538,
  "sp_home_away_split_edge": 0.001534,
  "away_runs_allowed_avg_5": 0.001526,
  "home_slg_avg_10": 0.001519,
  "combined_sb_avg_10": 0.001517,
  "away_bb_pct_avg_10": 0.001515,
  "away_team_k_bb_ratio_5": 0.001505,
  "home_sp_bb9_5": 0.001501,
  "combined_sp_k_pct": 0.001499,
  "home_sp_venue_starts": 0.001499,
  "away_runs_avg_20": 0.001496,
  "combined_sl_whiff_pct": 0.001486,
  "home_sp_career_whip_5": 0.001484,
  "bp_k9_edge": 0.00147,
  "away_sp_ip_avg_5": 0.001468,
  "home_bp_whip_5": 0.001466,
  "home_elo": 0.001461,
  "away_bp_era_7d": 0.001459,
  "away_runs_trend_5v20": 0.001459,
  "ump_bb9_x_away_team_bb": 0.001457,
  "away_runs_avg_10": 0.001456,
  "away_team_sp_k9_5": 0.001447,
  "away_k_pct_avg_10": 0.001446,
  "away_avg_avg_10": 0.001444,
  "away_era_5": 0.001439,
  "home_bp_era_10": 0.001439,
  "away_bp_era_5": 0.001422,
  "combined_runs_avg_10": 0.00142,
  "away_sb_pct_10": 0.001418,
  "away_bp_relievers_last_3d": 0.001418,
  "home_sp_fip_home_10": 0.00141,
  "away_sp_k9_5": 0.001406,
  "away_bullpen_ip_last_7": 0.001405,
  "away_bp_usage_per_rest": 0.001394,
  "team_era_5_diff": 0.001393,
  "away_runs_avg_5": 0.00138,
  "home_pythag": 0.00138,
  "away_sp_k_pct_5": 0.001378,
  "home_bp_k9_5": 0.001378,
  "home_bb_pct_avg_10": 0.001374,
  "home_losses": 0.001371,
  "home_lineup_iso_avg_10": 0.001368,
  "away_bp_era7_x_ip7": 0.001359,
  "home_sp_venue_era": 0.00135,
  "away_sp_ch_whiff_pct": 0.001349,
  "away_sp_fip_10": 0.001349,
  "h2h_slg_edge": 0.001343,
  "away_whip_5": 0.00134,
  "sp_era_regression_diff": 0.00134,
  "away_bb_pct_avg_5": 0.00134,
  "home_sp_sc_bb_pct": 0.001338,
  "away_sp_last_k_rate": 0.001334,
  "run_diff_avg_last_5_edge": 0.001331,
  "away_sp_sc_bb_pct": 0.00133,
  "bp_era_diff_5": 0.00133,
  "sp_venue_familiarity_diff": 0.001328,
  "total_vig_direction": 0.001325,
  "away_sp_sc_oz_swing_pct": 0.001315,
  "home_sp_era_5": 0.001306,
  "away_whip_10": 0.001304,
  "away_sp_sl_whiff_pct": 0.001301,
  "ump_k9_5": 0.001298,
  "home_bullpen_ip_last_3": 0.001297,
  "away_sp_sc_whiff_pct": 0.001284,
  "home_sp_career_era_10": 0.001279,
  "diff_sp_sc_bb_pct": 0.001278,
  "away_sp_era_home_10": 0.001271,
  "away_sp_fip_5": 0.001267,
  "away_ops_5": 0.001257,
  "diff_sp_sc_barrel_rate": 0.001227,
  "away_pythag_vs_record": 0.001225,
  "home_sp_whip_10": 0.001218,
  "home_lineup_slg_avg_10": 0.001217,
  "away_k9_5": 0.001213,
  "away_sp_k9_away_10": 0.001207,
  "away_sp_bb_pct_5": 0.001204,
  "home_bb9_5": 0.001201,
  "home_sp_sc_whiff_pct": 0.001194,
  "slg_edge_10": 0.001193,
  "sp_days_rest_diff": 0.001181,
  "home_runs_allowed_avg_5": 0.00118,
  "away_sp_ip_per_rest": 0.001176,
  "away_park_adj_runs_10": 0.001176,
  "away_h2h_slg": 0.001172,
  "away_lineup_hard_hit_avg": 0.001163,
  "away_obp_avg_10": 0.001159,
  "home_runs_allowed_avg_10": 0.001151,
  "batting_avg_avg_10_diff": 0.001131,
  "home_sp_era_away_10": 0.001126,
  "away_sp_fip_home_10": 0.001122,
  "home_sp_venue_fip": 0.001121,
  "home_runs_avg_10": 0.001117,
  "season_2024-regular": 0.001115,
  "sp_whip_5_diff": 0.001109,
  "home_hr_avg_10": 0.001107,
  "pen_exposure_era_diff": 0.001085,
  "home_sp_fip_5v20": 0.001073,
  "home_sp_era_trend_5v10": 0.001065,
  "away_bp_k9_5": 0.001064,
  "away_pythag": 0.001061,
  "bullpen_fatigue_7d_edge": 0.00106,
  "combined_obp_avg_10": 0.001058,
  "ops_diff_10": 0.00105,
  "away_sp_last_bb": 0.001042,
  "lineup_avg_edge": 0.001038,
  "home_obp_avg_5": 0.001036,
  "away_lineup_avg_avg_10": 0.001034,
  "sp_fip_trend_diff": 0.00103,
  "open_total_line": 0.001018,
  "batting_hr_avg_10_diff": 0.001009,
  "away_sp_fip_5v20": 0.001007,
  "home_iso_avg_5": 0.00099,
  "home_k9_5": 0.000984,
  "home_sp_era_park_adj_5": 0.000963,
  "home_sb_avg_5": 0.000962,
  "pythag_diff": 0.000936,
  "season_2025-regular": 0.000933,
  "away_k9_10": 0.000932,
  "away_losses": 0.000927,
  "park_adj_runs_diff": 0.000925,
  "win_pct_edge": 0.000912,
  "away_slg_avg_5": 0.0009,
  "away_ops_10": 0.000891,
  "sp_k_pct_5_diff": 0.000885,
  "home_k_pct_avg_10": 0.000882,
  "combined_fb_put_away": 0.000876,
  "away_form_vs_season": 0.000873,
  "away_implied_runs": 0.000868,
  "away_sb_avg_10": 0.000865,
  "temp_cold_penalty": 0.000864,
  "sp_last_quality_diff": 0.000854,
  "home_run_diff_avg_last_5": 0.000846,
  "sp_era_5_diff": 0.000835,
  "h2h_games_ytd": 0.000833,
  "team_hr_park_diff": 0.000822,
  "home_era_10": 0.000821,
  "home_bp_relievers_last_1d": 0.000812,
  "away_k_pct_avg_5": 0.000784,
  "home_avg_avg_5": 0.000781,
  "home_sb_trend": 0.000767,
  "abs_fb_velo_trend_away": 0.000754,
  "home_bb_pct_avg_5": 0.000751,
  "home_sp_sc_exit_velo": 0.000743,
  "batting_avg_avg_5_diff": 0.000742,
  "batting_iso_avg_10_diff": 0.000721,
  "away_hr_avg_10": 0.000695,
  "is_day_game": 0.000676,
  "home_runs_sd_10": 0.000662,
  "away_sp_last_quality": 0.000657,
  "away_team_sp_k9_10": 0.000656,
  "home_slg_avg_5": 0.000652,
  "total_line": 0.000629,
  "away_games_played": 0.00061,
  "home_sb_avg_10": 0.000599,
  "away_hr_avg_5": 0.000591,
  "home_ops_5": 0.000575,
  "open_run_line_home": 0.000569,
  "top4_bp_matchup_diff": 0.00054,
  "home_sp_last_ip": 0.000526,
  "season_days_elapsed": 0.000521,
  "home_whip_5": 0.000517,
  "home_k_pct_avg_5": 0.000503,
  "home_h2h_n": 0.000495,
  "away_sp_last_k": 0.000483,
  "away_sp_days_rest": 0.00045,
  "home_sp_last_bb": 0.000445,
  "home_wins_last_5": 0.000428,
  "home_hr_avg_5": 0.00042,
  "home_wins_last_10": 0.000417,
  "home_avg_avg_10": 0.000357,
  "park_run_factor": 0.000344,
  "away_runs_allowed_avg_10": 0.000303,
  "under_price": 0.000288,
  "home_sp_starts_in_window": 0.00023,
  "run_line_away_price": 0.000221,
  "away_sp_starts_in_window": 0.000186,
  "total_line_move_direction": 3e-06,
  "away_rest_days": 0.0,
  "market_total_vs_avg": 0.0,
  "total_line_move_large": 0.0,
  "run_line_move_large": 0.0,
  "home_sp_last_high_workload": 0.0,
  "away_sp_last_high_workload": 0.0,
  "home_sp_k_trend_5v10": 0.0,
  "away_sp_k_trend_5v10": 0.0,
  "home_sp_last_quality": 0.0,
  "ump_runs_per_game": 0.0,
  "home_hand_matchup_edge": 0.0,
  "home_obp_vs_sp_hand": 0.0,
  "away_hand_matchup_edge": 0.0,
  "away_obp_vs_sp_hand": 0.0,
  "platoon_matchup_diff": 0.0
}